plash_cli/__init__.py
plash_cli/_bash_magic.py
plash_cli/_modidx.py
plash_cli/auth.py
plash_cli/cli.py
plash_cli/assets/es256_public_key.pem
plash_cli-0.3.12.dist-info/licenses/LICENSE
plash_cli-0.3.12.dist-info/METADATA
plash_cli-0.3.12.dist-info/WHEEL
plash_cli-0.3.12.dist-info/entry_points.txt
plash_cli-0.3.12.dist-info/top_level.txt
plash_cli-0.3.12.dist-info/RECORD
